helga_haskell.py
setup.cfg
setup.py
helga_haskell.egg-info/PKG-INFO
helga_haskell.egg-info/SOURCES.txt
helga_haskell.egg-info/dependency_links.txt
helga_haskell.egg-info/entry_points.txt
helga_haskell.egg-info/requires.txt
helga_haskell.egg-info/top_level.txt
helga_haskell.egg-info/zip-safe