Metadata-Version: 1.0
Name: helga-haskell
Version: 0.2.1
Summary: Evaluate Haskell expressions using helga!
Home-page: https://github.com/carymrobbins/helga-haskell
Author: Cary M. Robbins
Author-email: carymrobbins@gmail.com
License: BSD3
Platform: UNKNOWN
